mlflow_hf_transformers/__init__.py
mlflow_hf_transformers-0.6.dist-info/METADATA
mlflow_hf_transformers-0.6.dist-info/WHEEL
mlflow_hf_transformers-0.6.dist-info/top_level.txt
mlflow_hf_transformers-0.6.dist-info/RECORD
